neuromorphic_drivers/neuromorphic_drivers.cpython-312-darwin.so
neuromorphic_drivers/mask.py
neuromorphic_drivers/orientation.py
neuromorphic_drivers/device.py
neuromorphic_drivers/__init__.py
neuromorphic_drivers/packet.py
neuromorphic_drivers/udev.py
neuromorphic_drivers/status.py
neuromorphic_drivers/generated/enums.py
neuromorphic_drivers/generated/devices_types.py
neuromorphic_drivers/generated/unions.py
neuromorphic_drivers/generated/devices/inivation_dvxplorer.py
neuromorphic_drivers/generated/devices/inivation_davis346.py
neuromorphic_drivers/generated/devices/prophesee_evk4.py
neuromorphic_drivers/generated/devices/prophesee_evk3_hd.py
neuromorphic_drivers/serde/binary.py
neuromorphic_drivers/serde/__init__.py
neuromorphic_drivers/serde/type.py
neuromorphic_drivers/serde/bincode.py
neuromorphic_drivers-0.16.4.dist-info/RECORD
neuromorphic_drivers-0.16.4.dist-info/WHEEL
neuromorphic_drivers-0.16.4.dist-info/entry_points.txt
neuromorphic_drivers-0.16.4.dist-info/METADATA
neuromorphic_drivers-0.16.4.dist-info/licenses/LICENSE
