Metadata-Version: 2.4
Name: neuromorphic_drivers
Version: 0.16.4
Requires-Dist: numpy>=1.26
License-File: LICENSE
Summary: Neuromorphic devices drivers
Author: International Centre for Neuromorphic Systems, Alexandre Marcireau
Requires-Python: >=3.9
Project-URL: homepage, https://github.com/neuromorphicsystems/neuromorphic-rs/
Project-URL: repository, https://github.com/neuromorphicsystems/neuromorphic-rs/
Project-URL: documentation, https://github.com/neuromorphicsystems/neuromorphic-rs/
